stackit/postgresflex/__init__.py
stackit/postgresflex/api/__init__.py
stackit/postgresflex/api/default_api.py
stackit/postgresflex/api_client.py
stackit/postgresflex/api_response.py
stackit/postgresflex/configuration.py
stackit/postgresflex/exceptions.py
stackit/postgresflex/models/__init__.py
stackit/postgresflex/models/acl.py
stackit/postgresflex/models/api_configuration.py
stackit/postgresflex/models/api_extension_config_load_response.py
stackit/postgresflex/models/api_extension_configure_response.py
stackit/postgresflex/models/api_extension_delete_response.py
stackit/postgresflex/models/api_extension_list.py
stackit/postgresflex/models/api_extension_load_response.py
stackit/postgresflex/models/api_install_response.py
stackit/postgresflex/models/api_installed_list_response.py
stackit/postgresflex/models/backup.py
stackit/postgresflex/models/clone_instance_payload.py
stackit/postgresflex/models/clone_instance_response.py
stackit/postgresflex/models/create_database_payload.py
stackit/postgresflex/models/create_instance_payload.py
stackit/postgresflex/models/create_instance_response.py
stackit/postgresflex/models/create_user_payload.py
stackit/postgresflex/models/create_user_response.py
stackit/postgresflex/models/error.py
stackit/postgresflex/models/extensions_configuration.py
stackit/postgresflex/models/extensions_extension_list_response.py
stackit/postgresflex/models/extensions_new_config.py
stackit/postgresflex/models/flavor.py
stackit/postgresflex/models/get_backup_response.py
stackit/postgresflex/models/get_user_response.py
stackit/postgresflex/models/instance.py
stackit/postgresflex/models/instance_create_database_response.py
stackit/postgresflex/models/instance_data_point.py
stackit/postgresflex/models/instance_database.py
stackit/postgresflex/models/instance_host.py
stackit/postgresflex/models/instance_host_metric.py
stackit/postgresflex/models/instance_list_databases_response.py
stackit/postgresflex/models/instance_list_instance.py
stackit_postgresflex-1.2.0.dist-info/METADATA
stackit_postgresflex-1.2.0.dist-info/WHEEL
stackit_postgresflex-1.2.0.dist-info/licenses/LICENSE.md
stackit_postgresflex-1.2.0.dist-info/licenses/NOTICE.txt
stackit_postgresflex-1.2.0.dist-info/RECORD
